[
    {
        "num": 0,
        "nombre": "CINESTAR",
        "ubi": "Centro",
        "capacidad": 300,
        "numero_salas": 5,
        "clasificacion": "A",
        "salas": [
            {
                "numero_sala": 1,
                "capacidad": 50,
                "formato_pantalla": "3D",
                "sonido": "Dolby Atmos",
                "tipo": "VIP",
                "funciones": [
                    {
                        "nf": 1,
                        "hora_inicio": "18:00",
                        "duracion": "2 horas",
                        "tipo_proyeccion": "Digital",
                        "precio_entrada": 10.5,
                        "pelicula": "Spider-Man: No Way Home"
                    }
                ]
            }
        ]
    },
    {
        "num": 1,
        "nombre": "CineStar",
        "ubi": "NORTEE",
        "capacidad": 200,
        "numero_salas": 3,
        "clasificacion": "B",
        "salas": [
            {
                "numero_sala": 0,
                "capacidad": 60,
                "formato_pantalla": "2D",
                "sonido": "DTS",
                "tipo": "Regular",
                "funciones": [
                    {
                        "nf": 0,
                        "hora_inicio": "20:30",
                        "duracion": "2.5 horas",
                        "tipo_proyeccion": "IMAX",
                        "precio_entrada": 15.0,
                        "pelicula": "Gwen Stacy: Into the Spider-Verse"
                    },
                    {
                        "nf": 1,
                        "hora_inicio": "22",
                        "duracion": "22",
                        "tipo_proyeccion": "22",
                        "precio_entrada": 22.0,
                        "pelicula": "22"
                    }
                ]
            }
        ]
    },
    {
        "num": 2,
        "nombre": "22",
        "ubi": "22",
        "capacidad": 22,
        "numero_salas": 222,
        "clasificacion": "22",
        "salas": [
            {
                "numero_sala": 1,
                "capacidad": 22,
                "formato_pantalla": "22",
                "sonido": "22",
                "tipo": "22",
                "funciones": [
                    {
                        "nf": 0,
                        "hora_inicio": "22",
                        "duracion": "22",
                        "tipo_proyeccion": "22",
                        "precio_entrada": 22.0,
                        "pelicula": "22"
                    }
                ]
            }
        ]
    },
    {
        "num": 3,
        "nombre": "22",
        "ubi": "22",
        "capacidad": 22,
        "numero_salas": 22,
        "clasificacion": "22",
        "salas": [
            {
                "numero_sala": 1,
                "capacidad": 22,
                "formato_pantalla": "22",
                "sonido": "22",
                "tipo": "22",
                "funciones": []
            }
        ]
    },
    {
        "num": 4,
        "nombre": "22",
        "ubi": "22",
        "capacidad": 22,
        "numero_salas": 22,
        "clasificacion": "222",
        "salas": [
            {
                "numero_sala": 1,
                "capacidad": 22,
                "formato_pantalla": "22",
                "sonido": "222",
                "tipo": "22",
                "funciones": [
                    {
                        "nf": 0,
                        "hora_inicio": "22",
                        "duracion": "22",
                        "tipo_proyeccion": "22",
                        "precio_entrada": 22.0,
                        "pelicula": "22"
                    }
                ]
            }
        ]
    },
    {
        "num": 5,
        "nombre": "22",
        "ubi": "22",
        "capacidad": 22,
        "numero_salas": 22,
        "clasificacion": "22",
        "salas": [
            {
                "numero_sala": 1,
                "capacidad": 22,
                "formato_pantalla": "22",
                "sonido": "22",
                "tipo": "22",
                "funciones": [
                    {
                        "nf": 0,
                        "hora_inicio": "22",
                        "duracion": "22",
                        "tipo_proyeccion": "22",
                        "precio_entrada": 22.0,
                        "pelicula": "22"
                    }
                ]
            }
        ]
    },
    {
        "num": 6,
        "nombre": "22",
        "ubi": "22",
        "capacidad": 22,
        "numero_salas": 22,
        "clasificacion": "22",
        "salas": [
            {
                "numero_sala": 1,
                "capacidad": 22,
                "formato_pantalla": "22",
                "sonido": "22",
                "tipo": "22",
                "funciones": [
                    {
                        "nf": 0,
                        "hora_inicio": "22",
                        "duracion": "22",
                        "tipo_proyeccion": "22",
                        "precio_entrada": 22.0,
                        "pelicula": "22"
                    },
                    {
                        "nf": 1,
                        "hora_inicio": "22",
                        "duracion": "22",
                        "tipo_proyeccion": "2",
                        "precio_entrada": 22.0,
                        "pelicula": "22"
                    }
                ]
            }
        ]
    }
]